{
    "key": "group_5b33fd74b2e83",
    "title": "Custom Main Menu",
    "fields": [
        {
            "key": "field_5b33fd7c31748",
            "label": "Menu Items",
            "name": "menu_items",
            "type": "repeater",
            "instructions": "",
            "required": 0,
            "conditional_logic": 0,
            "wrapper": {
                "width": "",
                "class": "",
                "id": ""
            },
            "collapsed": "",
            "min": 0,
            "max": 0,
            "layout": "row",
            "button_label": "Add Navigation Item",
            "sub_fields": [
                {
                    "key": "field_5b3402831957f",
                    "label": "Page Link",
                    "name": "page_link",
                    "type": "link",
                    "instructions": "",
                    "required": 0,
                    "conditional_logic": 0,
                    "wrapper": {
                        "width": "100",
                        "class": "",
                        "id": ""
                    },
                    "return_format": "url"
                },
                {
                    "key": "field_5b33fd9231749",
                    "label": "Category Title",
                    "name": "category_title",
                    "type": "text",
                    "instructions": "",
                    "required": 0,
                    "conditional_logic": 0,
                    "wrapper": {
                        "width": "33",
                        "class": "",
                        "id": ""
                    },
                    "default_value": "",
                    "placeholder": "",
                    "prepend": "",
                    "append": "",
                    "maxlength": ""
                },
                {
                    "key": "field_5b33fdd93174a",
                    "label": "Thumbnail Image",
                    "name": "thumbnail_image",
                    "type": "image",
                    "instructions": "",
                    "required": 0,
                    "conditional_logic": 0,
                    "wrapper": {
                        "width": "33",
                        "class": "",
                        "id": ""
                    },
                    "return_format": "array",
                    "preview_size": "thumbnail",
                    "library": "all",
                    "min_width": "",
                    "min_height": "",
                    "min_size": "",
                    "max_width": "",
                    "max_height": "",
                    "max_size": "",
                    "mime_types": ""
                },
                {
                    "key": "field_5b33fdf33174b",
                    "label": "Short Text",
                    "name": "short_text",
                    "type": "textarea",
                    "instructions": "",
                    "required": 0,
                    "conditional_logic": 0,
                    "wrapper": {
                        "width": "33",
                        "class": "",
                        "id": ""
                    },
                    "default_value": "",
                    "placeholder": "",
                    "maxlength": "",
                    "rows": "",
                    "new_lines": ""
                }
            ]
        }
    ],
    "location": [
        [
            {
                "param": "options_page",
                "operator": "==",
                "value": "acf-options-custom-main-menu"
            }
        ]
    ],
    "menu_order": 0,
    "position": "normal",
    "style": "seamless",
    "label_placement": "top",
    "instruction_placement": "label",
    "hide_on_screen": "",
    "active": 1,
    "description": "",
    "modified": 1530137843
}